orjsonl/__init__.py
orjsonl/orjsonl.py
orjsonl/py.typed
orjsonl-0.3.1.dist-info/METADATA
orjsonl-0.3.1.dist-info/WHEEL
orjsonl-0.3.1.dist-info/licenses/LICENSE
orjsonl-0.3.1.dist-info/RECORD
